{"get":"fixtures","parameters":{"league":"253","to":"2024-07-31","from":"2024-07-01","timezone":"America/Bogota","season":"2024"},"errors":[],"results":68,"paging":{"current":1,"total":1},"response":[{"fixture":{"id":1151049,"referee":"Rubiel Vazquez, USA","timezone":"America/Bogota","date":"2024-07-03T18:30:00-05:00","timestamp":1720049400,"periods":{"first":1720049400,"second":1720053000},"venue":{"id":18659,"name":"Bank of America Stadium","city":"Charlotte, North Carolina"},"status":{"long":"Match Finished","short":"FT","elapsed":90}},"league":{"id":253,"name":"Major League Soccer","country":"USA","logo":"https://media.api-sports.io/football/leagues/253.png","flag":"https://media.api-sports.io/flags/us.svg","season":2024,"round":"Regular Season - 31"},"teams":{"home":{"id":18310,"name":"Charlotte","logo":"https://media.api-sports.io/football/teams/18310.png","winner":false},"away":{"id":9568,"name":"Inter Miami","logo":"https://media.api-sports.io/football/teams/9568.png","winner":true}},"goals":{"home":1,"away":2},"score":{"halftime":{"home":1,"away":1},"fulltime":{"home":1,"away":2},"extratime":{"home":null,"away":null},"penalty":{"home":null,"away":null}}},{"fixture":{"id":1151050,"referee":"Joseph Dickerson, USA","timezone":"America/Bogota","date":"2024-07-03T17:30:00-05:00","timestamp":1720045800,"periods":{"first":1720045800,"second":1720049400},"venue":{"id":12667,"name":"Lower.com Field","city":"Columbus, Ohio"},"status":{"long":"Match Finished","short":"FT","elapsed":90}},"league":{"id":253,"name":"Major League Soccer","country":"USA","logo":"https://media.api-sports.io/football/leagues/253.png","flag":"https://media.api-sports.io/flags/us.svg","season":2024,"round":"Regular Season - 31"},"teams":{"home":{"id":1613,"name":"Columbus Crew","logo":"https://media.api-sports.io/football/teams/1613.png","winner":true},"away":{"id":9569,"name":"Nashville SC","logo":"https://media.api-sports.io/football/teams/9569.png","winner":false}},"goals":{"home":2,"away":0},"score":{"halftime":{"home":1,"away":0},"fulltime":{"home":2,"away":0},"extratime":{"home":null,"away":null},"penalty":{"home":null,"away":null}}},{"fixture":{"id":1151051,"referee":"Alexis Da Silva, USA","timezone":"America/Bogota","date":"2024-07-03T18:30:00-05:00","timestamp":1720049400,"periods":{"first":1720049400,"second":1720053000},"venue":{"id":1613,"name":"Audi Field","city":"Washington, District of Columbia"},"status":{"long":"Match Finished","short":"FT","elapsed":90}},"league":{"id":253,"name":"Major League Soccer","country":"USA","logo":"https://media.api-sports.io/football/leagues/253.png","flag":"https://media.api-sports.io/flags/us.svg","season":2024,"round":"Regular Season - 31"},"teams":{"home":{"id":1615,"name":"DC United","logo":"https://media.api-sports.io/football/teams/1615.png","winner":false},"away":{"id":2242,"name":"FC Cincinnati","logo":"https://media.api-sports.io/football/teams/2242.png","winner":true}},"goals":{"home":2,"away":3},"score":{"halftime":{"home":1,"away":2},"fulltime":{"home":2,"away":3},"extratime":{"home":null,"away":null},"penalty":{"home":null,"away":null}}},{"fixture":{"id":1151052,"referee":"Jair Antonio Maruffo, USA","timezone":"America/Bogota","date":"2024-07-03T18:45:00-05:00","timestamp":1720050300,"periods":{"first":1720050300,"second":1720053900},"venue":{"id":1618,"name":"Gillette Stadium","city":"Foxborough, Massachusetts"},"status":{"long":"Match Finished","short":"FT","elapsed":90}},"league":{"id":253,"name":"Major League Soccer","country":"USA","logo":"https://media.api-sports.io/football/leagues/253.png","flag":"https://media.api-sports.io/flags/us.svg","season":2024,"round":"Regular Season - 31"},"teams":{"home":{"id":1609,"name":"New England Revolution","logo":"https://media.api-sports.io/football/teams/1609.png","winner":true},"away":{"id":1608,"name":"Atlanta United FC","logo":"https://media.api-sports.io/football/teams/1608.png","winner":false}},"goals":{"home":2,"away":1},"score":{"halftime":{"home":2,"away":0},"fulltime":{"home":2,"away":1},"extratime":{"home":null,"away":null},"penalty":{"home":null,"away":null}}},{"fixture":{"id":1151053,"referee":"Marcos de Oliveira, USA","timezone":"America/Bogota","date":"2024-07-03T18:30:00-05:00","timestamp":1720049400,"periods":{"first":1720049400,"second":1720053000},"venue":{"id":null,"name":"Citi Field","city":"Flushing"},"status":{"long":"Match Finished","short":"FT","elapsed":90}},"league":{"id":253,"name":"Major League Soccer","country":"USA","logo":"https://media.api-sports.io/football/leagues/253.png","flag":"https://media.api-sports.io/flags/us.svg","season":2024,"round":"Regular Season - 31"},"teams":{"home":{"id":1604,"name":"New York City FC","logo":"https://media.api-sports.io/football/teams/1604.png","winner":true},"away":{"id":1614,"name":"CF Montreal","logo":"https://media.api-sports.io/football/teams/1614.png","winner":false}},"goals":{"home":2,"away":0},"score":{"halftime":{"home":1,"away":0},"fulltime":{"home":2,"away":0},"extratime":{"home":null,"away":null},"penalty":{"home":null,"away":null}}},{"fixture":{"id":1151054,"referee":"Mark Allatin, USA","timezone":"America/Bogota","date":"2024-07-03T18:30:00-05:00","timestamp":1720049400,"periods":{"first":1720049400,"second":1720053000},"venue":{"id":312,"name":"BMO Field","city":"Toronto, Ontario"},"status":{"long":"Match Finished","short":"FT","elapsed":90}},"league":{"id":253,"name":"Major League Soccer","country":"USA","logo":"https://media.api-sports.io/football/leagues/253.png","flag":"https://media.api-sports.io/flags/us.svg","season":2024,"round":"Regular Season - 31"},"teams":{"home":{"id":1601,"name":"Toronto FC","logo":"https://media.api-sports.io/football/teams/1601.png","winner":false},"away":{"id":1598,"name":"Orlando City SC","logo":"https://media.api-sports.io/football/teams/1598.png","winner":true}},"goals":{"home":1,"away":2},"score":{"halftime":{"home":1,"away":2},"fulltime":{"home":1,"away":2},"extratime":{"home":null,"away":null},"penalty":{"home":null,"away":null}}},{"fixture":{"id":1151055,"referee":"Abdou Ndiaye, USA","timezone":"America/Bogota","date":"2024-07-03T19:30:00-05:00","timestamp":1720053000,"periods":{"first":1720053000,"second":1720056600},"venue":{"id":1609,"name":"Soldier Field","city":"Chicago, Illinois"},"status":{"long":"Match Finished","short":"FT","elapsed":90}},"league":{"id":253,"name":"Major League Soccer","country":"USA","logo":"https://media.api-sports.io/football/leagues/253.png","flag":"https://media.api-sports.io/flags/us.svg","season":2024,"round":"Regular Season - 31"},"teams":{"home":{"id":1607,"name":"Chicago Fire","logo":"https://media.api-sports.io/football/teams/1607.png","winner":true},"away":{"id":1599,"name":"Philadelphia Union","logo":"https://media.api-sports.io/football/teams/1599.png","winner":false}},"goals":{"home":4,"away":3},"score":{"halftime":{"home":1,"away":2},"fulltime":{"home":4,"away":3},"extratime":{"home":null,"away":null},"penalty":{"home":null,"away":null}}},{"fixture":{"id":1151056,"referee":"Victor Rivas, USA","timezone":"America/Bogota","date":"2024-07-03T19:30:00-05:00","timestamp":1720053000,"periods":{"first":1720053000,"second":1720056600},"venue":{"id":1617,"name":"Allianz Field","city":"Saint Paul, Minnesota"},"status":{"long":"Match Finished","short":"FT","elapsed":90}},"league":{"id":253,"name":"Major League Soccer","country":"USA","logo":"https://media.api-sports.io/football/leagues/253.png","flag":"https://media.api-sports.io/flags/us.svg","season":2024,"round":"Regular Season - 31"},"teams":{"home":{"id":1612,"name":"Minnesota United FC","logo":"https://media.api-sports.io/football/teams/1612.png","winner":false},"away":{"id":1603,"name":"Vancouver Whitecaps","logo":"https://media.api-sports.io/football/teams/1603.png","winner":true}},"goals":{"home":1,"away":3},"score":{"halftime":{"home":1,"away":2},"fulltime":{"home":1,"away":3},"extratime":{"home":null,"away":null},"penalty":{"home":null,"away":null}}},{"fixture":{"id":1151057,"referee":"Malik Badawi, USA","timezone":"America/Bogota","date":"2024-07-03T19:30:00-05:00","timestamp":1720053000,"periods":{"first":1720053000,"second":1720056600},"venue":{"id":19408,"name":"CITYPARK","city":"St. Louis, Missouri"},"status":{"long":"Match Finished","short":"FT","elapsed":90}},"league":{"id":253,"name":"Major League Soccer","country":"USA","logo":"https://media.api-sports.io/football/leagues/253.png","flag":"https://media.api-sports.io/flags/us.svg","season":2024,"round":"Regular Season - 31"},"teams":{"home":{"id":20787,"name":"St. Louis City","logo":"https://media.api-sports.io/football/teams/20787.png","winner":true},"away":{"id":1596,"name":"San Jose Earthquakes","logo":"https://media.api-sports.io/football/teams/1596.png","winner":false}},"goals":{"home":2,"away":0},"score":{"halftime":{"home":2,"away":0},"fulltime":{"home":2,"away":0},"extratime":{"home":null,"away":null},"penalty":{"home":null,"away":null}}},{"fixture":{"id":1151058,"referee":"Allen Chapman, USA","timezone":"America/Bogota","date":"2024-07-03T20:30:00-05:00","timestamp":1720056600,"periods":{"first":1720056600,"second":1720060200},"venue":{"id":19223,"name":"America First Field","city":"Sandy, Utah"},"status":{"long":"Match Finished","short":"FT","elapsed":90}},"league":{"id":253,"name":"Major League Soccer","country":"USA","logo":"https://media.api-sports.io/football/leagues/253.png","flag":"https://media.api-sports.io/flags/us.svg","season":2024,"round":"Regular Season - 31"},"teams":{"home":{"id":1606,"name":"Real Salt Lake","logo":"https://media.api-sports.io/football/teams/1606.png","winner":true},"away":{"id":1600,"name":"Houston Dynamo","logo":"https://media.api-sports.io/football/teams/1600.png","winner":false}},"goals":{"home":3,"away":2},"score":{"halftime":{"home":2,"away":1},"fulltime":{"home":3,"away":2},"extratime":{"home":null,"away":null},"penalty":{"home":null,"away":null}}},{"fixture":{"id":1151059,"referee":"Rosendo Mendoza, USA","timezone":"America/Bogota","date":"2024-07-04T19:30:00-05:00","timestamp":1720139400,"periods":{"first":1720139400,"second":1720143000},"venue":{"id":1612,"name":"Toyota Stadium","city":"Frisco, Texas"},"status":{"long":"Match Finished","short":"FT","elapsed":90}},"league":{"id":253,"name":"Major League Soccer","country":"USA","logo":"https://media.api-sports.io/football/leagues/253.png","flag":"https://media.api-sports.io/flags/us.svg","season":2024,"round":"Regular Season - 32"},"teams":{"home":{"id":1597,"name":"FC Dallas","logo":"https://media.api-sports.io/football/teams/1597.png","winner":true},"away":{"id":1617,"name":"Portland Timbers","logo":"https://media.api-sports.io/football/teams/1617.png","winner":false}},"goals":{"home":3,"away":2},"score":{"halftime":{"home":0,"away":1},"fulltime":{"home":3,"away":2},"extratime":{"home":null,"away":null},"penalty":{"home":null,"away":null}}},{"fixture":{"id":1151060,"referee":"Sergiy Boyko, Ukraine","timezone":"America/Bogota","date":"2024-07-04T20:30:00-05:00","timestamp":1720143000,"periods":{"first":1720143000,"second":1720146600},"venue":{"id":1610,"name":"Dick's Sporting Goods Park","city":"Commerce City, Colorado"},"status":{"long":"Match Finished","short":"FT","elapsed":90}},"league":{"id":253,"name":"Major League Soccer","country":"USA","logo":"https://media.api-sports.io/football/leagues/253.png","flag":"https://media.api-sports.io/flags/us.svg","season":2024,"round":"Regular Season - 32"},"teams":{"home":{"id":1610,"name":"Colorado Rapids","logo":"https://media.api-sports.io/football/teams/1610.png","winner":true},"away":{"id":1611,"name":"Sporting Kansas City","logo":"https://media.api-sports.io/football/teams/1611.png","winner":false}},"goals":{"home":2,"away":1},"score":{"halftime":{"home":0,"away":0},"fulltime":{"home":2,"away":1},"extratime":{"home":null,"away":null},"penalty":{"home":null,"away":null}}},{"fixture":{"id":1151061,"referee":"Drew Fischer, Canada","timezone":"America/Bogota","date":"2024-07-04T21:30:00-05:00","timestamp":1720146600,"periods":{"first":1720146600,"second":1720150200},"venue":{"id":1616,"name":"Rose Bowl","city":"Pasadena, California"},"status":{"long":"Match Finished","short":"FT","elapsed":90}},"league":{"id":253,"name":"Major League Soccer","country":"USA","logo":"https://media.api-sports.io/football/leagues/253.png","flag":"https://media.api-sports.io/flags/us.svg","season":2024,"round":"Regular Season - 32"},"teams":{"home":{"id":1605,"name":"Los Angeles Galaxy","logo":"https://media.api-sports.io/football/teams/1605.png","winner":false},"away":{"id":1616,"name":"Los Angeles FC","logo":"https://media.api-sports.io/football/teams/1616.png","winner":true}},"goals":{"home":1,"away":2},"score":{"halftime":{"home":0,"away":2},"fulltime":{"home":1,"away":2},"extratime":{"home":null,"away":null},"penalty":{"home":null,"away":null}}},{"fixture":{"id":1151062,"referee":"Chris Penso, USA","timezone":"America/Bogota","date":"2024-07-06T18:30:00-05:00","timestamp":1720308600,"periods":{"first":1720308600,"second":1720312200},"venue":{"id":19229,"name":"TQL Stadium","city":"Cincinnati, Ohio"},"status":{"long":"Match Finished","short":"FT","elapsed":90}},"league":{"id":253,"name":"Major League Soccer","country":"USA","logo":"https://media.api-sports.io/football/leagues/253.png","flag":"https://media.api-sports.io/flags/us.svg","season":2024,"round":"Regular Season - 32"},"teams":{"home":{"id":2242,"name":"FC Cincinnati","logo":"https://media.api-sports.io/football/teams/2242.png","winner":true},"away":{"id":9568,"name":"Inter Miami","logo":"https://media.api-sports.io/football/teams/9568.png","winner":false}},"goals":{"home":6,"away":1},"score":{"halftime":{"home":4,"away":1},"fulltime":{"home":6,"away":1},"extratime":{"home":null,"away":null},"penalty":{"home":null,"away":null}}},{"fixture":{"id":1151063,"referee":"Ted Unkel, USA","timezone":"America/Bogota","date":"2024-07-06T18:30:00-05:00","timestamp":1720308600,"periods":{"first":1720308600,"second":1720312200},"venue":{"id":12667,"name":"Lower.com Field","city":"Columbus, Ohio"},"status":{"long":"Match Finished","short":"FT","elapsed":90}},"league":{"id":253,"name":"Major League Soccer","country":"USA","logo":"https://media.api-sports.io/football/leagues/253.png","flag":"https://media.api-sports.io/flags/us.svg","season":2024,"round":"Regular Season - 32"},"teams":{"home":{"id":1613,"name":"Columbus Crew","logo":"https://media.api-sports.io/football/teams/1613.png","winner":true},"away":{"id":1601,"name":"Toronto FC","logo":"https://media.api-sports.io/football/teams/1601.png","winner":false}},"goals":{"home":4,"away":0},"score":{"halftime":{"home":1,"away":0},"fulltime":{"home":4,"away":0},"extratime":{"home":null,"away":null},"penalty":{"home":null,"away":null}}},{"fixture":{"id":1151064,"referee":"Guido Gonzales Jr, USA","timezone":"America/Bogota","date":"2024-07-06T18:30:00-05:00","timestamp":1720308600,"periods":{"first":1720308600,"second":1720312200},"venue":{"id":310,"name":"Stade Saputo","city":"Montreal, Quebec"},"status":{"long":"Match Finished","short":"FT","elapsed":90}},"league":{"id":253,"name":"Major League Soccer","country":"USA","logo":"https://media.api-sports.io/football/leagues/253.png","flag":"https://media.api-sports.io/flags/us.svg","season":2024,"round":"Regular Season - 32"},"teams":{"home":{"id":1614,"name":"CF Montreal","logo":"https://media.api-sports.io/football/teams/1614.png","winner":null},"away":{"id":1603,"name":"Vancouver Whitecaps","logo":"https://media.api-sports.io/football/teams/1603.png","winner":null}},"goals":{"home":1,"away":1},"score":{"halftime":{"home":0,"away":1},"fulltime":{"home":1,"away":1},"extratime":{"home":null,"away":null},"penalty":{"home":null,"away":null}}},{"fixture":{"id":1151065,"referee":"Lukasz Szpala, USA","timezone":"America/Bogota","date":"2024-07-06T18:30:00-05:00","timestamp":1720308600,"periods":{"first":1720308600,"second":1720312200},"venue":{"id":20500,"name":"Inter&Co Stadium","city":"Orlando, Florida"},"status":{"long":"Match Finished","short":"FT","elapsed":90}},"league":{"id":253,"name":"Major League Soccer","country":"USA","logo":"https://media.api-sports.io/football/leagues/253.png","flag":"https://media.api-sports.io/flags/us.svg","season":2024,"round":"Regular Season - 32"},"teams":{"home":{"id":1598,"name":"Orlando City SC","logo":"https://media.api-sports.io/football/teams/1598.png","winner":true},"away":{"id":1615,"name":"DC United","logo":"https://media.api-sports.io/football/teams/1615.png","winner":false}},"goals":{"home":5,"away":0},"score":{"halftime":{"home":3,"away":0},"fulltime":{"home":5,"away":0},"extratime":{"home":null,"away":null},"penalty":{"home":null,"away":null}}},{"fixture":{"id":1151066,"referee":"Filip Dujic, USA","timezone":"America/Bogota","date":"2024-07-06T18:30:00-05:00","timestamp":1720308600,"periods":{"first":1720308600,"second":1720312200},"venue":{"id":1620,"name":"Subaru Park","city":"Chester, Pennsylvania"},"status":{"long":"Match Finished","short":"FT","elapsed":90}},"league":{"id":253,"name":"Major League Soccer","country":"USA","logo":"https://media.api-sports.io/football/leagues/253.png","flag":"https://media.api-sports.io/flags/us.svg","season":2024,"round":"Regular Season - 32"},"teams":{"home":{"id":1599,"name":"Philadelphia Union","logo":"https://media.api-sports.io/football/teams/1599.png","winner":null},"away":{"id":1602,"name":"New York Red Bulls","logo":"https://media.api-sports.io/football/teams/1602.png","winner":null}},"goals":{"home":0,"away":0},"score":{"halftime":{"home":0,"away":0},"fulltime":{"home":0,"away":0},"extratime":{"home":null,"away":null},"penalty":{"home":null,"away":null}}},{"fixture":{"id":1151067,"referee":"T. Ford","timezone":"America/Bogota","date":"2024-07-06T19:30:00-05:00","timestamp":1720312200,"periods":{"first":1720312200,"second":1720315800},"venue":{"id":11535,"name":"Q2 Stadium","city":"Austin, Texas"},"status":{"long":"Match Finished","short":"FT","elapsed":90}},"league":{"id":253,"name":"Major League Soccer","country":"USA","logo":"https://media.api-sports.io/football/leagues/253.png","flag":"https://media.api-sports.io/flags/us.svg","season":2024,"round":"Regular Season - 32"},"teams":{"home":{"id":16489,"name":"Austin","logo":"https://media.api-sports.io/football/teams/16489.png","winner":true},"away":{"id":1604,"name":"New York City FC","logo":"https://media.api-sports.io/football/teams/1604.png","winner":false}},"goals":{"home":2,"away":1},"score":{"halftime":{"home":1,"away":1},"fulltime":{"home":2,"away":1},"extratime":{"home":null,"away":null},"penalty":{"home":null,"away":null}}},{"fixture":{"id":1151068,"referee":"R. Vazquez","timezone":"America/Bogota","date":"2024-07-06T20:30:00-05:00","timestamp":1720315800,"periods":{"first":1720315800,"second":1720319400},"venue":{"id":19223,"name":"America First Field","city":"Sandy, Utah"},"status":{"long":"Match Finished","short":"FT","elapsed":90}},"league":{"id":253,"name":"Major League Soccer","country":"USA","logo":"https://media.api-sports.io/football/leagues/253.png","flag":"https://media.api-sports.io/flags/us.svg","season":2024,"round":"Regular Season - 32"},"teams":{"home":{"id":1606,"name":"Real Salt Lake","logo":"https://media.api-sports.io/football/teams/1606.png","winner":true},"away":{"id":1608,"name":"Atlanta United FC","logo":"https://media.api-sports.io/football/teams/1608.png","winner":false}},"goals":{"home":5,"away":2},"score":{"halftime":{"home":1,"away":1},"fulltime":{"home":5,"away":2},"extratime":{"home":null,"away":null},"penalty":{"home":null,"away":null}}},{"fixture":{"id":1151069,"referee":"I. Pekmic","timezone":"America/Bogota","date":"2024-07-06T21:30:00-05:00","timestamp":1720319400,"periods":{"first":1720319400,"second":1720323000},"venue":{"id":11534,"name":"Lumen Field","city":"Seattle, Washington"},"status":{"long":"Match Finished","short":"FT","elapsed":90}},"league":{"id":253,"name":"Major League Soccer","country":"USA","logo":"https://media.api-sports.io/football/leagues/253.png","flag":"https://media.api-sports.io/flags/us.svg","season":2024,"round":"Regular Season - 33"},"teams":{"home":{"id":1595,"name":"Seattle Sounders","logo":"https://media.api-sports.io/football/teams/1595.png","winner":true},"away":{"id":1609,"name":"New England Revolution","logo":"https://media.api-sports.io/football/teams/1609.png","winner":false}},"goals":{"home":2,"away":0},"score":{"halftime":{"home":1,"away":0},"fulltime":{"home":2,"away":0},"extratime":{"home":null,"away":null},"penalty":{"home":null,"away":null}}},{"fixture":{"id":1151071,"referee":"Natalie Simon, USA","timezone":"America/Bogota","date":"2024-07-07T19:30:00-05:00","timestamp":1720398600,"periods":{"first":1720398600,"second":1720402200},"venue":{"id":1615,"name":"Children's Mercy Park","city":"Kansas City, Kansas"},"status":{"long":"Match Finished","short":"FT","elapsed":90}},"league":{"id":253,"name":"Major League Soccer","country":"USA","logo":"https://media.api-sports.io/football/leagues/253.png","flag":"https://media.api-sports.io/flags/us.svg","season":2024,"round":"Regular Season - 33"},"teams":{"home":{"id":1611,"name":"Sporting Kansas City","logo":"https://media.api-sports.io/football/teams/1611.png","winner":true},"away":{"id":1597,"name":"FC Dallas","logo":"https://media.api-sports.io/football/teams/1597.png","winner":false}},"goals":{"home":3,"away":2},"score":{"halftime":{"home":2,"away":1},"fulltime":{"home":3,"away":2},"extratime":{"home":null,"away":null},"penalty":{"home":null,"away":null}}},{"fixture":{"id":1151072,"referee":"Ramy Touchan, USA","timezone":"America/Bogota","date":"2024-07-07T19:30:00-05:00","timestamp":1720398600,"periods":{"first":1720398600,"second":1720402200},"venue":{"id":11918,"name":"PayPal Park","city":"San Jose, California"},"status":{"long":"Match Finished","short":"FT","elapsed":90}},"league":{"id":253,"name":"Major League Soccer","country":"USA","logo":"https://media.api-sports.io/football/leagues/253.png","flag":"https://media.api-sports.io/flags/us.svg","season":2024,"round":"Regular Season - 33"},"teams":{"home":{"id":1596,"name":"San Jose Earthquakes","logo":"https://media.api-sports.io/football/teams/1596.png","winner":true},"away":{"id":1607,"name":"Chicago Fire","logo":"https://media.api-sports.io/football/teams/1607.png","winner":false}},"goals":{"home":1,"away":0},"score":{"halftime":{"home":0,"away":0},"fulltime":{"home":1,"away":0},"extratime":{"home":null,"away":null},"penalty":{"home":null,"away":null}}},{"fixture":{"id":1151073,"referee":"Drew Fischer, Canada","timezone":"America/Bogota","date":"2024-07-07T20:30:00-05:00","timestamp":1720402200,"periods":{"first":1720402200,"second":1720405800},"venue":{"id":1610,"name":"Dick's Sporting Goods Park","city":"Commerce City, Colorado"},"status":{"long":"Match Finished","short":"FT","elapsed":90}},"league":{"id":253,"name":"Major League Soccer","country":"USA","logo":"https://media.api-sports.io/football/leagues/253.png","flag":"https://media.api-sports.io/flags/us.svg","season":2024,"round":"Regular Season - 33"},"teams":{"home":{"id":1610,"name":"Colorado Rapids","logo":"https://media.api-sports.io/football/teams/1610.png","winner":true},"away":{"id":20787,"name":"St. Louis City","logo":"https://media.api-sports.io/football/teams/20787.png","winner":false}},"goals":{"home":4,"away":1},"score":{"halftime":{"home":2,"away":1},"fulltime":{"home":4,"away":1},"extratime":{"home":null,"away":null},"penalty":{"home":null,"away":null}}},{"fixture":{"id":1151074,"referee":"Pierre-Luc Lauziere, USA","timezone":"America/Bogota","date":"2024-07-07T21:30:00-05:00","timestamp":1720405800,"periods":{"first":1720405800,"second":1720409400},"venue":{"id":1616,"name":"Dignity Health Sports Park","city":"Carson, California"},"status":{"long":"Match Finished","short":"FT","elapsed":90}},"league":{"id":253,"name":"Major League Soccer","country":"USA","logo":"https://media.api-sports.io/football/leagues/253.png","flag":"https://media.api-sports.io/flags/us.svg","season":2024,"round":"Regular Season - 33"},"teams":{"home":{"id":1605,"name":"Los Angeles Galaxy","logo":"https://media.api-sports.io/football/teams/1605.png","winner":true},"away":{"id":1612,"name":"Minnesota United FC","logo":"https://media.api-sports.io/football/teams/1612.png","winner":false}},"goals":{"home":2,"away":1},"score":{"halftime":{"home":1,"away":0},"fulltime":{"home":2,"away":1},"extratime":{"home":null,"away":null},"penalty":{"home":null,"away":null}}},{"fixture":{"id":1151075,"referee":"Jon Freemon, USA","timezone":"America/Bogota","date":"2024-07-07T21:30:00-05:00","timestamp":1720405800,"periods":{"first":1720405800,"second":1720409400},"venue":{"id":1748,"name":"Providence Park","city":"Portland, Oregon"},"status":{"long":"Match Finished","short":"FT","elapsed":90}},"league":{"id":253,"name":"Major League Soccer","country":"USA","logo":"https://media.api-sports.io/football/leagues/253.png","flag":"https://media.api-sports.io/flags/us.svg","season":2024,"round":"Regular Season - 33"},"teams":{"home":{"id":1617,"name":"Portland Timbers","logo":"https://media.api-sports.io/football/teams/1617.png","winner":true},"away":{"id":9569,"name":"Nashville SC","logo":"https://media.api-sports.io/football/teams/9569.png","winner":false}},"goals":{"home":4,"away":1},"score":{"halftime":{"home":4,"away":0},"fulltime":{"home":4,"away":1},"extratime":{"home":null,"away":null},"penalty":{"home":null,"away":null}}},{"fixture":{"id":1151076,"referee":"Guido Gonzales Jr, USA","timezone":"America/Bogota","date":"2024-07-13T18:30:00-05:00","timestamp":1720913400,"periods":{"first":1720913400,"second":1720917000},"venue":{"id":19229,"name":"TQL Stadium","city":"Cincinnati, Ohio"},"status":{"long":"Match Finished","short":"FT","elapsed":90}},"league":{"id":253,"name":"Major League Soccer","country":"USA","logo":"https://media.api-sports.io/football/leagues/253.png","flag":"https://media.api-sports.io/flags/us.svg","season":2024,"round":"Regular Season - 34"},"teams":{"home":{"id":2242,"name":"FC Cincinnati","logo":"https://media.api-sports.io/football/teams/2242.png","winner":false},"away":{"id":18310,"name":"Charlotte","logo":"https://media.api-sports.io/football/teams/18310.png","winner":true}},"goals":{"home":1,"away":3},"score":{"halftime":{"home":1,"away":2},"fulltime":{"home":1,"away":3},"extratime":{"home":null,"away":null},"penalty":{"home":null,"away":null}}},{"fixture":{"id":1151077,"referee":"Filip Dujic, USA","timezone":"America/Bogota","date":"2024-07-13T18:30:00-05:00","timestamp":1720913400,"periods":{"first":1720913400,"second":1720917000},"venue":{"id":1613,"name":"Audi Field","city":"Washington, District of Columbia"},"status":{"long":"Match Finished","short":"FT","elapsed":90}},"league":{"id":253,"name":"Major League Soccer","country":"USA","logo":"https://media.api-sports.io/football/leagues/253.png","flag":"https://media.api-sports.io/flags/us.svg","season":2024,"round":"Regular Season - 33"},"teams":{"home":{"id":1615,"name":"DC United","logo":"https://media.api-sports.io/football/teams/1615.png","winner":true},"away":{"id":9569,"name":"Nashville SC","logo":"https://media.api-sports.io/football/teams/9569.png","winner":false}},"goals":{"home":2,"away":1},"score":{"halftime":{"home":0,"away":1},"fulltime":{"home":2,"away":1},"extratime":{"home":null,"away":null},"penalty":{"home":null,"away":null}}},{"fixture":{"id":1151078,"referee":"Ted Unkel, USA","timezone":"America/Bogota","date":"2024-07-13T18:30:00-05:00","timestamp":1720913400,"periods":{"first":1720913400,"second":1720917000},"venue":{"id":310,"name":"Stade Saputo","city":"Montreal, Quebec"},"status":{"long":"Match Finished","short":"FT","elapsed":90}},"league":{"id":253,"name":"Major League Soccer","country":"USA","logo":"https://media.api-sports.io/football/leagues/253.png","flag":"https://media.api-sports.io/flags/us.svg","season":2024,"round":"Regular Season - 33"},"teams":{"home":{"id":1614,"name":"CF Montreal","logo":"https://media.api-sports.io/football/teams/1614.png","winner":true},"away":{"id":1608,"name":"Atlanta United FC","logo":"https://media.api-sports.io/football/teams/1608.png","winner":false}},"goals":{"home":1,"away":0},"score":{"halftime":{"home":0,"away":0},"fulltime":{"home":1,"away":0},"extratime":{"home":null,"away":null},"penalty":{"home":null,"away":null}}},{"fixture":{"id":1151079,"referee":"Sergiy Boyko, Ukraine","timezone":"America/Bogota","date":"2024-07-13T18:30:00-05:00","timestamp":1720913400,"periods":{"first":1720913400,"second":1720917000},"venue":{"id":1618,"name":"Gillette Stadium","city":"Foxborough, Massachusetts"},"status":{"long":"Match Finished","short":"FT","elapsed":90}},"league":{"id":253,"name":"Major League Soccer","country":"USA","logo":"https://media.api-sports.io/football/leagues/253.png","flag":"https://media.api-sports.io/flags/us.svg","season":2024,"round":"Regular Season - 33"},"teams":{"home":{"id":1609,"name":"New England Revolution","logo":"https://media.api-sports.io/football/teams/1609.png","winner":false},"away":{"id":1598,"name":"Orlando City SC","logo":"https://media.api-sports.io/football/teams/1598.png","winner":true}},"goals":{"home":1,"away":3},"score":{"halftime":{"home":1,"away":0},"fulltime":{"home":1,"away":3},"extratime":{"home":null,"away":null},"penalty":{"home":null,"away":null}}},{"fixture":{"id":1151080,"referee":"Allen Chapman, USA","timezone":"America/Bogota","date":"2024-07-13T18:30:00-05:00","timestamp":1720913400,"periods":{"first":1720913400,"second":1720917000},"venue":{"id":312,"name":"BMO Field","city":"Toronto, Ontario"},"status":{"long":"Match Finished","short":"FT","elapsed":90}},"league":{"id":253,"name":"Major League Soccer","country":"USA","logo":"https://media.api-sports.io/football/leagues/253.png","flag":"https://media.api-sports.io/flags/us.svg","season":2024,"round":"Regular Season - 33"},"teams":{"home":{"id":1601,"name":"Toronto FC","logo":"https://media.api-sports.io/football/teams/1601.png","winner":true},"away":{"id":1599,"name":"Philadelphia Union","logo":"https://media.api-sports.io/football/teams/1599.png","winner":false}},"goals":{"home":2,"away":1},"score":{"halftime":{"home":0,"away":1},"fulltime":{"home":2,"away":1},"extratime":{"home":null,"away":null},"penalty":{"home":null,"away":null}}},{"fixture":{"id":1151081,"referee":"Jair Antonio Maruffo, USA","timezone":"America/Bogota","date":"2024-07-13T19:30:00-05:00","timestamp":1720917000,"periods":{"first":1720917000,"second":1720920600},"venue":{"id":11535,"name":"Q2 Stadium","city":"Austin, Texas"},"status":{"long":"Match Finished","short":"FT","elapsed":90}},"league":{"id":253,"name":"Major League Soccer","country":"USA","logo":"https://media.api-sports.io/football/leagues/253.png","flag":"https://media.api-sports.io/flags/us.svg","season":2024,"round":"Regular Season - 34"},"teams":{"home":{"id":16489,"name":"Austin","logo":"https://media.api-sports.io/football/teams/16489.png","winner":false},"away":{"id":1595,"name":"Seattle Sounders","logo":"https://media.api-sports.io/football/teams/1595.png","winner":true}},"goals":{"home":0,"away":1},"score":{"halftime":{"home":0,"away":0},"fulltime":{"home":0,"away":1},"extratime":{"home":null,"away":null},"penalty":{"home":null,"away":null}}},{"fixture":{"id":1151082,"referee":"Rosendo Mendoza, USA","timezone":"America/Bogota","date":"2024-07-13T19:30:00-05:00","timestamp":1720917000,"periods":{"first":1720917000,"second":1720920600},"venue":{"id":1609,"name":"Soldier Field","city":"Chicago, Illinois"},"status":{"long":"Match Finished","short":"FT","elapsed":90}},"league":{"id":253,"name":"Major League Soccer","country":"USA","logo":"https://media.api-sports.io/football/leagues/253.png","flag":"https://media.api-sports.io/flags/us.svg","season":2024,"round":"Regular Season - 34"},"teams":{"home":{"id":1607,"name":"Chicago Fire","logo":"https://media.api-sports.io/football/teams/1607.png","winner":null},"away":{"id":1604,"name":"New York City FC","logo":"https://media.api-sports.io/football/teams/1604.png","winner":null}},"goals":{"home":0,"away":0},"score":{"halftime":{"home":0,"away":0},"fulltime":{"home":0,"away":0},"extratime":{"home":null,"away":null},"penalty":{"home":null,"away":null}}},{"fixture":{"id":1151083,"referee":"Ramy Touchan, USA","timezone":"America/Bogota","date":"2024-07-13T19:30:00-05:00","timestamp":1720917000,"periods":{"first":1720917000,"second":1720920600},"venue":{"id":1612,"name":"Toyota Stadium","city":"Frisco, Texas"},"status":{"long":"Match Finished","short":"FT","elapsed":90}},"league":{"id":253,"name":"Major League Soccer","country":"USA","logo":"https://media.api-sports.io/football/leagues/253.png","flag":"https://media.api-sports.io/flags/us.svg","season":2024,"round":"Regular Season - 34"},"teams":{"home":{"id":1597,"name":"FC Dallas","logo":"https://media.api-sports.io/football/teams/1597.png","winner":true},"away":{"id":1605,"name":"Los Angeles Galaxy","logo":"https://media.api-sports.io/football/teams/1605.png","winner":false}},"goals":{"home":2,"away":0},"score":{"halftime":{"home":1,"away":0},"fulltime":{"home":2,"away":0},"extratime":{"home":null,"away":null},"penalty":{"home":null,"away":null}}},{"fixture":{"id":1151084,"referee":"Jon Freemon, USA","timezone":"America/Bogota","date":"2024-07-13T19:30:00-05:00","timestamp":1720917000,"periods":{"first":1720917000,"second":1720920600},"venue":{"id":19418,"name":"Shell Energy Stadium","city":"Houston, Texas"},"status":{"long":"Match Finished","short":"FT","elapsed":90}},"league":{"id":253,"name":"Major League Soccer","country":"USA","logo":"https://media.api-sports.io/football/leagues/253.png","flag":"https://media.api-sports.io/flags/us.svg","season":2024,"round":"Regular Season - 34"},"teams":{"home":{"id":1600,"name":"Houston Dynamo","logo":"https://media.api-sports.io/football/teams/1600.png","winner":null},"away":{"id":1612,"name":"Minnesota United FC","logo":"https://media.api-sports.io/football/teams/1612.png","winner":null}},"goals":{"home":1,"away":1},"score":{"halftime":{"home":0,"away":0},"fulltime":{"home":1,"away":1},"extratime":{"home":null,"away":null},"penalty":{"home":null,"away":null}}},{"fixture":{"id":1151085,"referee":"Pierre-Luc Lauziere, USA","timezone":"America/Bogota","date":"2024-07-13T19:30:00-05:00","timestamp":1720917000,"periods":{"first":1720917000,"second":1720920600},"venue":{"id":19408,"name":"CITYPARK","city":"St. Louis, Missouri"},"status":{"long":"Match Finished","short":"FT","elapsed":90}},"league":{"id":253,"name":"Major League Soccer","country":"USA","logo":"https://media.api-sports.io/football/leagues/253.png","flag":"https://media.api-sports.io/flags/us.svg","season":2024,"round":"Regular Season - 34"},"teams":{"home":{"id":20787,"name":"St. Louis City","logo":"https://media.api-sports.io/football/teams/20787.png","winner":false},"away":{"id":1603,"name":"Vancouver Whitecaps","logo":"https://media.api-sports.io/football/teams/1603.png","winner":true}},"goals":{"home":1,"away":4},"score":{"halftime":{"home":1,"away":2},"fulltime":{"home":1,"away":4},"extratime":{"home":null,"away":null},"penalty":{"home":null,"away":null}}},{"fixture":{"id":1151086,"referee":"Tim Ford, USA","timezone":"America/Bogota","date":"2024-07-13T20:30:00-05:00","timestamp":1720920600,"periods":{"first":1720920600,"second":1720924200},"venue":{"id":1610,"name":"Dick's Sporting Goods Park","city":"Commerce City, Colorado"},"status":{"long":"Match Finished","short":"FT","elapsed":90}},"league":{"id":253,"name":"Major League Soccer","country":"USA","logo":"https://media.api-sports.io/football/leagues/253.png","flag":"https://media.api-sports.io/flags/us.svg","season":2024,"round":"Regular Season - 34"},"teams":{"home":{"id":1610,"name":"Colorado Rapids","logo":"https://media.api-sports.io/football/teams/1610.png","winner":null},"away":{"id":1602,"name":"New York Red Bulls","logo":"https://media.api-sports.io/football/teams/1602.png","winner":null}},"goals":{"home":1,"away":1},"score":{"halftime":{"home":0,"away":1},"fulltime":{"home":1,"away":1},"extratime":{"home":null,"away":null},"penalty":{"home":null,"away":null}}},{"fixture":{"id":1151087,"referee":"Lukasz Szpala, USA","timezone":"America/Bogota","date":"2024-07-13T21:30:00-05:00","timestamp":1720924200,"periods":{"first":1720924200,"second":1720927800},"venue":{"id":19419,"name":"BMO Stadium","city":"Los Angeles, California"},"status":{"long":"Match Finished","short":"FT","elapsed":90}},"league":{"id":253,"name":"Major League Soccer","country":"USA","logo":"https://media.api-sports.io/football/leagues/253.png","flag":"https://media.api-sports.io/flags/us.svg","season":2024,"round":"Regular Season - 34"},"teams":{"home":{"id":1616,"name":"Los Angeles FC","logo":"https://media.api-sports.io/football/teams/1616.png","winner":false},"away":{"id":1613,"name":"Columbus Crew","logo":"https://media.api-sports.io/football/teams/1613.png","winner":true}},"goals":{"home":1,"away":5},"score":{"halftime":{"home":0,"away":1},"fulltime":{"home":1,"away":5},"extratime":{"home":null,"away":null},"penalty":{"home":null,"away":null}}},{"fixture":{"id":1151088,"referee":"Joseph Dickerson, USA","timezone":"America/Bogota","date":"2024-07-13T21:25:00-05:00","timestamp":1720923900,"periods":{"first":1720923900,"second":1720927500},"venue":{"id":1748,"name":"Providence Park","city":"Portland, Oregon"},"status":{"long":"Match Finished","short":"FT","elapsed":90}},"league":{"id":253,"name":"Major League Soccer","country":"USA","logo":"https://media.api-sports.io/football/leagues/253.png","flag":"https://media.api-sports.io/flags/us.svg","season":2024,"round":"Regular Season - 34"},"teams":{"home":{"id":1617,"name":"Portland Timbers","logo":"https://media.api-sports.io/football/teams/1617.png","winner":true},"away":{"id":1606,"name":"Real Salt Lake","logo":"https://media.api-sports.io/football/teams/1606.png","winner":false}},"goals":{"home":3,"away":0},"score":{"halftime":{"home":1,"away":0},"fulltime":{"home":3,"away":0},"extratime":{"home":null,"away":null},"penalty":{"home":null,"away":null}}},{"fixture":{"id":1151089,"referee":"Alexis Da Silva, USA","timezone":"America/Bogota","date":"2024-07-13T21:30:00-05:00","timestamp":1720924200,"periods":{"first":1720924200,"second":1720927800},"venue":{"id":11918,"name":"PayPal Park","city":"San Jose, California"},"status":{"long":"Match Finished","short":"FT","elapsed":90}},"league":{"id":253,"name":"Major League Soccer","country":"USA","logo":"https://media.api-sports.io/football/leagues/253.png","flag":"https://media.api-sports.io/flags/us.svg","season":2024,"round":"Regular Season - 34"},"teams":{"home":{"id":1596,"name":"San Jose Earthquakes","logo":"https://media.api-sports.io/football/teams/1596.png","winner":false},"away":{"id":1611,"name":"Sporting Kansas City","logo":"https://media.api-sports.io/football/teams/1611.png","winner":true}},"goals":{"home":1,"away":2},"score":{"halftime":{"home":0,"away":0},"fulltime":{"home":1,"away":2},"extratime":{"home":null,"away":null},"penalty":{"home":null,"away":null}}},{"fixture":{"id":1151090,"referee":"Lukasz Szpala, USA","timezone":"America/Bogota","date":"2024-07-17T18:30:00-05:00","timestamp":1721259000,"periods":{"first":1721259000,"second":1721262600},"venue":{"id":1898,"name":"Mercedes-Benz Stadium","city":"Atlanta, Georgia"},"status":{"long":"Match Finished","short":"FT","elapsed":90}},"league":{"id":253,"name":"Major League Soccer","country":"USA","logo":"https://media.api-sports.io/football/leagues/253.png","flag":"https://media.api-sports.io/flags/us.svg","season":2024,"round":"Regular Season - 35"},"teams":{"home":{"id":1608,"name":"Atlanta United FC","logo":"https://media.api-sports.io/football/teams/1608.png","winner":null},"away":{"id":1604,"name":"New York City FC","logo":"https://media.api-sports.io/football/teams/1604.png","winner":null}},"goals":{"home":2,"away":2},"score":{"halftime":{"home":2,"away":0},"fulltime":{"home":2,"away":2},"extratime":{"home":null,"away":null},"penalty":{"home":null,"away":null}}},{"fixture":{"id":1151091,"referee":"Filip Dujic, USA","timezone":"America/Bogota","date":"2024-07-17T18:30:00-05:00","timestamp":1721259000,"periods":{"first":1721259000,"second":1721262600},"venue":{"id":19229,"name":"TQL Stadium","city":"Cincinnati, Ohio"},"status":{"long":"Match Finished","short":"FT","elapsed":90}},"league":{"id":253,"name":"Major League Soccer","country":"USA","logo":"https://media.api-sports.io/football/leagues/253.png","flag":"https://media.api-sports.io/flags/us.svg","season":2024,"round":"Regular Season - 35"},"teams":{"home":{"id":2242,"name":"FC Cincinnati","logo":"https://media.api-sports.io/football/teams/2242.png","winner":false},"away":{"id":1607,"name":"Chicago Fire","logo":"https://media.api-sports.io/football/teams/1607.png","winner":true}},"goals":{"home":0,"away":1},"score":{"halftime":{"home":0,"away":0},"fulltime":{"home":0,"away":1},"extratime":{"home":null,"away":null},"penalty":{"home":null,"away":null}}},{"fixture":{"id":1151092,"referee":"Victor Rivas, USA","timezone":"America/Bogota","date":"2024-07-17T18:30:00-05:00","timestamp":1721259000,"periods":{"first":1721259000,"second":1721262600},"venue":{"id":12667,"name":"Lower.com Field","city":"Columbus, Ohio"},"status":{"long":"Match Finished","short":"FT","elapsed":90}},"league":{"id":253,"name":"Major League Soccer","country":"USA","logo":"https://media.api-sports.io/football/leagues/253.png","flag":"https://media.api-sports.io/flags/us.svg","season":2024,"round":"Regular Season - 35"},"teams":{"home":{"id":1613,"name":"Columbus Crew","logo":"https://media.api-sports.io/football/teams/1613.png","winner":null},"away":{"id":18310,"name":"Charlotte","logo":"https://media.api-sports.io/football/teams/18310.png","winner":null}},"goals":{"home":1,"away":1},"score":{"halftime":{"home":1,"away":0},"fulltime":{"home":1,"away":1},"extratime":{"home":null,"away":null},"penalty":{"home":null,"away":null}}},{"fixture":{"id":1151093,"referee":"Jair Antonio Maruffo, USA","timezone":"America/Bogota","date":"2024-07-17T18:30:00-05:00","timestamp":1721259000,"periods":{"first":1721259000,"second":1721262600},"venue":{"id":20764,"name":"Chase Stadium","city":"Fort Lauderdale, Florida"},"status":{"long":"Match Finished","short":"FT","elapsed":90}},"league":{"id":253,"name":"Major League Soccer","country":"USA","logo":"https://media.api-sports.io/football/leagues/253.png","flag":"https://media.api-sports.io/flags/us.svg","season":2024,"round":"Regular Season - 35"},"teams":{"home":{"id":9568,"name":"Inter Miami","logo":"https://media.api-sports.io/football/teams/9568.png","winner":true},"away":{"id":1601,"name":"Toronto FC","logo":"https://media.api-sports.io/football/teams/1601.png","winner":false}},"goals":{"home":3,"away":1},"score":{"halftime":{"home":1,"away":0},"fulltime":{"home":3,"away":1},"extratime":{"home":null,"away":null},"penalty":{"home":null,"away":null}}},{"fixture":{"id":1151094,"referee":"Sergiy Boyko, Ukraine","timezone":"America/Bogota","date":"2024-07-17T18:30:00-05:00","timestamp":1721259000,"periods":{"first":1721259000,"second":1721262600},"venue":{"id":1619,"name":"Red Bull Arena","city":"Harrison, New Jersey"},"status":{"long":"Match Finished","short":"FT","elapsed":90}},"league":{"id":253,"name":"Major League Soccer","country":"USA","logo":"https://media.api-sports.io/football/leagues/253.png","flag":"https://media.api-sports.io/flags/us.svg","season":2024,"round":"Regular Season - 35"},"teams":{"home":{"id":1602,"name":"New York Red Bulls","logo":"https://media.api-sports.io/football/teams/1602.png","winner":null},"away":{"id":1614,"name":"CF Montreal","logo":"https://media.api-sports.io/football/teams/1614.png","winner":null}},"goals":{"home":2,"away":2},"score":{"halftime":{"home":1,"away":0},"fulltime":{"home":2,"away":2},"extratime":{"home":null,"away":null},"penalty":{"home":null,"away":null}}},{"fixture":{"id":1151095,"referee":"Rubiel Vazquez, USA","timezone":"America/Bogota","date":"2024-07-17T18:30:00-05:00","timestamp":1721259000,"periods":{"first":1721259000,"second":1721262600},"venue":{"id":1620,"name":"Subaru Park","city":"Chester, Pennsylvania"},"status":{"long":"Match Finished","short":"FT","elapsed":90}},"league":{"id":253,"name":"Major League Soccer","country":"USA","logo":"https://media.api-sports.io/football/leagues/253.png","flag":"https://media.api-sports.io/flags/us.svg","season":2024,"round":"Regular Season - 35"},"teams":{"home":{"id":1599,"name":"Philadelphia Union","logo":"https://media.api-sports.io/football/teams/1599.png","winner":true},"away":{"id":1609,"name":"New England Revolution","logo":"https://media.api-sports.io/football/teams/1609.png","winner":false}},"goals":{"home":5,"away":1},"score":{"halftime":{"home":3,"away":0},"fulltime":{"home":5,"away":1},"extratime":{"home":null,"away":null},"penalty":{"home":null,"away":null}}},{"fixture":{"id":1151096,"referee":"Villarrea Armando, USA","timezone":"America/Bogota","date":"2024-07-17T19:30:00-05:00","timestamp":1721262600,"periods":{"first":1721262600,"second":1721266200},"venue":{"id":1612,"name":"Toyota Stadium","city":"Frisco, Texas"},"status":{"long":"Match Finished","short":"FT","elapsed":90}},"league":{"id":253,"name":"Major League Soccer","country":"USA","logo":"https://media.api-sports.io/football/leagues/253.png","flag":"https://media.api-sports.io/flags/us.svg","season":2024,"round":"Regular Season - 35"},"teams":{"home":{"id":1597,"name":"FC Dallas","logo":"https://media.api-sports.io/football/teams/1597.png","winner":true},"away":{"id":16489,"name":"Austin","logo":"https://media.api-sports.io/football/teams/16489.png","winner":false}},"goals":{"home":3,"away":1},"score":{"halftime":{"home":1,"away":1},"fulltime":{"home":3,"away":1},"extratime":{"home":null,"away":null},"penalty":{"home":null,"away":null}}},{"fixture":{"id":1151097,"referee":"Mark Allatin, USA","timezone":"America/Bogota","date":"2024-07-17T19:30:00-05:00","timestamp":1721262600,"periods":{"first":1721262600,"second":1721266200},"venue":{"id":1617,"name":"Allianz Field","city":"Saint Paul, Minnesota"},"status":{"long":"Match Finished","short":"FT","elapsed":90}},"league":{"id":253,"name":"Major League Soccer","country":"USA","logo":"https://media.api-sports.io/football/leagues/253.png","flag":"https://media.api-sports.io/flags/us.svg","season":2024,"round":"Regular Season - 35"},"teams":{"home":{"id":1612,"name":"Minnesota United FC","logo":"https://media.api-sports.io/football/teams/1612.png","winner":false},"away":{"id":1615,"name":"DC United","logo":"https://media.api-sports.io/football/teams/1615.png","winner":true}},"goals":{"home":2,"away":3},"score":{"halftime":{"home":1,"away":1},"fulltime":{"home":2,"away":3},"extratime":{"home":null,"away":null},"penalty":{"home":null,"away":null}}},{"fixture":{"id":1151098,"referee":"Pierre-Luc Lauziere, USA","timezone":"America/Bogota","date":"2024-07-17T19:30:00-05:00","timestamp":1721262600,"periods":{"first":1721262600,"second":1721266200},"venue":{"id":19357,"name":"GEODIS Park","city":"Nashville, Tennessee"},"status":{"long":"Match Finished","short":"FT","elapsed":90}},"league":{"id":253,"name":"Major League Soccer","country":"USA","logo":"https://media.api-sports.io/football/leagues/253.png","flag":"https://media.api-sports.io/flags/us.svg","season":2024,"round":"Regular Season - 35"},"teams":{"home":{"id":9569,"name":"Nashville SC","logo":"https://media.api-sports.io/football/teams/9569.png","winner":false},"away":{"id":1598,"name":"Orlando City SC","logo":"https://media.api-sports.io/football/teams/1598.png","winner":true}},"goals":{"home":0,"away":3},"score":{"halftime":{"home":0,"away":2},"fulltime":{"home":0,"away":3},"extratime":{"home":null,"away":null},"penalty":{"home":null,"away":null}}},{"fixture":{"id":1151099,"referee":"Ismir Pekmic, USA","timezone":"America/Bogota","date":"2024-07-17T21:30:00-05:00","timestamp":1721269800,"periods":{"first":1721269800,"second":1721273400},"venue":{"id":1616,"name":"Dignity Health Sports Park","city":"Carson, California"},"status":{"long":"Match Finished","short":"FT","elapsed":90}},"league":{"id":253,"name":"Major League Soccer","country":"USA","logo":"https://media.api-sports.io/football/leagues/253.png","flag":"https://media.api-sports.io/flags/us.svg","season":2024,"round":"Regular Season - 35"},"teams":{"home":{"id":1605,"name":"Los Angeles Galaxy","logo":"https://media.api-sports.io/football/teams/1605.png","winner":true},"away":{"id":1610,"name":"Colorado Rapids","logo":"https://media.api-sports.io/football/teams/1610.png","winner":false}},"goals":{"home":3,"away":2},"score":{"halftime":{"home":3,"away":2},"fulltime":{"home":3,"away":2},"extratime":{"home":null,"away":null},"penalty":{"home":null,"away":null}}},{"fixture":{"id":1151100,"referee":"Guido Gonzales Jr, USA","timezone":"America/Bogota","date":"2024-07-17T21:45:00-05:00","timestamp":1721270700,"periods":{"first":1721270700,"second":1721274300},"venue":{"id":19419,"name":"BMO Stadium","city":"Los Angeles, California"},"status":{"long":"Match Finished","short":"FT","elapsed":90}},"league":{"id":253,"name":"Major League Soccer","country":"USA","logo":"https://media.api-sports.io/football/leagues/253.png","flag":"https://media.api-sports.io/flags/us.svg","season":2024,"round":"Regular Season - 35"},"teams":{"home":{"id":1616,"name":"Los Angeles FC","logo":"https://media.api-sports.io/football/teams/1616.png","winner":null},"away":{"id":1606,"name":"Real Salt Lake","logo":"https://media.api-sports.io/football/teams/1606.png","winner":null}},"goals":{"home":1,"away":1},"score":{"halftime":{"home":1,"away":1},"fulltime":{"home":1,"away":1},"extratime":{"home":null,"away":null},"penalty":{"home":null,"away":null}}},{"fixture":{"id":1151101,"referee":"Natalie Simon, USA","timezone":"America/Bogota","date":"2024-07-17T21:30:00-05:00","timestamp":1721269800,"periods":{"first":1721269800,"second":1721273400},"venue":{"id":11918,"name":"PayPal Park","city":"San Jose, California"},"status":{"long":"Match Finished","short":"FT","elapsed":90}},"league":{"id":253,"name":"Major League Soccer","country":"USA","logo":"https://media.api-sports.io/football/leagues/253.png","flag":"https://media.api-sports.io/flags/us.svg","season":2024,"round":"Regular Season - 35"},"teams":{"home":{"id":1596,"name":"San Jose Earthquakes","logo":"https://media.api-sports.io/football/teams/1596.png","winner":false},"away":{"id":1600,"name":"Houston Dynamo","logo":"https://media.api-sports.io/football/teams/1600.png","winner":true}},"goals":{"home":0,"away":1},"score":{"halftime":{"home":0,"away":0},"fulltime":{"home":0,"away":1},"extratime":{"home":null,"away":null},"penalty":{"home":null,"away":null}}},{"fixture":{"id":1151102,"referee":"Alexis Da Silva, USA","timezone":"America/Bogota","date":"2024-07-17T21:30:00-05:00","timestamp":1721269800,"periods":{"first":1721269800,"second":1721273400},"venue":{"id":11534,"name":"Lumen Field","city":"Seattle, Washington"},"status":{"long":"Match Finished","short":"FT","elapsed":90}},"league":{"id":253,"name":"Major League Soccer","country":"USA","logo":"https://media.api-sports.io/football/leagues/253.png","flag":"https://media.api-sports.io/flags/us.svg","season":2024,"round":"Regular Season - 35"},"teams":{"home":{"id":1595,"name":"Seattle Sounders","logo":"https://media.api-sports.io/football/teams/1595.png","winner":true},"away":{"id":20787,"name":"St. Louis City","logo":"https://media.api-sports.io/football/teams/20787.png","winner":false}},"goals":{"home":2,"away":0},"score":{"halftime":{"home":1,"away":0},"fulltime":{"home":2,"away":0},"extratime":{"home":null,"away":null},"penalty":{"home":null,"away":null}}},{"fixture":{"id":1151103,"referee":"Marcos de Oliveira, USA","timezone":"America/Bogota","date":"2024-07-17T21:30:00-05:00","timestamp":1721269800,"periods":{"first":1721269800,"second":1721273400},"venue":{"id":19445,"name":"BC Place","city":"Vancouver, British Columbia"},"status":{"long":"Match Finished","short":"FT","elapsed":90}},"league":{"id":253,"name":"Major League Soccer","country":"USA","logo":"https://media.api-sports.io/football/leagues/253.png","flag":"https://media.api-sports.io/flags/us.svg","season":2024,"round":"Regular Season - 35"},"teams":{"home":{"id":1603,"name":"Vancouver Whitecaps","logo":"https://media.api-sports.io/football/teams/1603.png","winner":true},"away":{"id":1611,"name":"Sporting Kansas City","logo":"https://media.api-sports.io/football/teams/1611.png","winner":false}},"goals":{"home":2,"away":1},"score":{"halftime":{"home":1,"away":0},"fulltime":{"home":2,"away":1},"extratime":{"home":null,"away":null},"penalty":{"home":null,"away":null}}},{"fixture":{"id":1151104,"referee":"Fotis Bazakos, USA","timezone":"America/Bogota","date":"2024-07-20T21:30:00-05:00","timestamp":1721529000,"periods":{"first":1721529000,"second":1721532600},"venue":{"id":19445,"name":"BC Place","city":"Vancouver, British Columbia"},"status":{"long":"Match Finished","short":"FT","elapsed":90}},"league":{"id":253,"name":"Major League Soccer","country":"USA","logo":"https://media.api-sports.io/football/leagues/253.png","flag":"https://media.api-sports.io/flags/us.svg","season":2024,"round":"Regular Season - 35"},"teams":{"home":{"id":1603,"name":"Vancouver Whitecaps","logo":"https://media.api-sports.io/football/teams/1603.png","winner":false},"away":{"id":1600,"name":"Houston Dynamo","logo":"https://media.api-sports.io/football/teams/1600.png","winner":true}},"goals":{"home":3,"away":4},"score":{"halftime":{"home":0,"away":2},"fulltime":{"home":3,"away":4},"extratime":{"home":null,"away":null},"penalty":{"home":null,"away":null}}},{"fixture":{"id":1151105,"referee":"Rosendo Mendoza, USA","timezone":"America/Bogota","date":"2024-07-20T18:30:00-05:00","timestamp":1721518200,"periods":{"first":1721518200,"second":1721521800},"venue":{"id":1898,"name":"Mercedes-Benz Stadium","city":"Atlanta, Georgia"},"status":{"long":"Match Finished","short":"FT","elapsed":90}},"league":{"id":253,"name":"Major League Soccer","country":"USA","logo":"https://media.api-sports.io/football/leagues/253.png","flag":"https://media.api-sports.io/flags/us.svg","season":2024,"round":"Regular Season - 35"},"teams":{"home":{"id":1608,"name":"Atlanta United FC","logo":"https://media.api-sports.io/football/teams/1608.png","winner":true},"away":{"id":1613,"name":"Columbus Crew","logo":"https://media.api-sports.io/football/teams/1613.png","winner":false}},"goals":{"home":2,"away":1},"score":{"halftime":{"home":0,"away":1},"fulltime":{"home":2,"away":1},"extratime":{"home":null,"away":null},"penalty":{"home":null,"away":null}}},{"fixture":{"id":1151106,"referee":"Marcos de Oliveira, USA","timezone":"America/Bogota","date":"2024-07-20T18:30:00-05:00","timestamp":1721518200,"periods":{"first":1721518200,"second":1721521800},"venue":{"id":20764,"name":"Chase Stadium","city":"Fort Lauderdale, Florida"},"status":{"long":"Match Finished","short":"FT","elapsed":90}},"league":{"id":253,"name":"Major League Soccer","country":"USA","logo":"https://media.api-sports.io/football/leagues/253.png","flag":"https://media.api-sports.io/flags/us.svg","season":2024,"round":"Regular Season - 35"},"teams":{"home":{"id":9568,"name":"Inter Miami","logo":"https://media.api-sports.io/football/teams/9568.png","winner":true},"away":{"id":1607,"name":"Chicago Fire","logo":"https://media.api-sports.io/football/teams/1607.png","winner":false}},"goals":{"home":2,"away":1},"score":{"halftime":{"home":1,"away":0},"fulltime":{"home":2,"away":1},"extratime":{"home":null,"away":null},"penalty":{"home":null,"away":null}}},{"fixture":{"id":1151107,"referee":"Villarrea Armando, USA","timezone":"America/Bogota","date":"2024-07-20T18:30:00-05:00","timestamp":1721518200,"periods":{"first":1721518200,"second":1721521800},"venue":{"id":310,"name":"Stade Saputo","city":"Montreal, Quebec"},"status":{"long":"Match Finished","short":"FT","elapsed":90}},"league":{"id":253,"name":"Major League Soccer","country":"USA","logo":"https://media.api-sports.io/football/leagues/253.png","flag":"https://media.api-sports.io/flags/us.svg","season":2024,"round":"Regular Season - 35"},"teams":{"home":{"id":1614,"name":"CF Montreal","logo":"https://media.api-sports.io/football/teams/1614.png","winner":false},"away":{"id":1601,"name":"Toronto FC","logo":"https://media.api-sports.io/football/teams/1601.png","winner":true}},"goals":{"home":0,"away":1},"score":{"halftime":{"home":0,"away":1},"fulltime":{"home":0,"away":1},"extratime":{"home":null,"away":null},"penalty":{"home":null,"away":null}}},{"fixture":{"id":1151108,"referee":"Pierre-Luc Lauziere, USA","timezone":"America/Bogota","date":"2024-07-20T18:30:00-05:00","timestamp":1721518200,"periods":{"first":1721518200,"second":1721521800},"venue":{"id":1618,"name":"Gillette Stadium","city":"Foxborough, Massachusetts"},"status":{"long":"Match Finished","short":"FT","elapsed":90}},"league":{"id":253,"name":"Major League Soccer","country":"USA","logo":"https://media.api-sports.io/football/leagues/253.png","flag":"https://media.api-sports.io/flags/us.svg","season":2024,"round":"Regular Season - 35"},"teams":{"home":{"id":1609,"name":"New England Revolution","logo":"https://media.api-sports.io/football/teams/1609.png","winner":null},"away":{"id":1597,"name":"FC Dallas","logo":"https://media.api-sports.io/football/teams/1597.png","winner":null}},"goals":{"home":1,"away":1},"score":{"halftime":{"home":0,"away":0},"fulltime":{"home":1,"away":1},"extratime":{"home":null,"away":null},"penalty":{"home":null,"away":null}}},{"fixture":{"id":1151109,"referee":"Ted Unkel, USA","timezone":"America/Bogota","date":"2024-07-20T18:30:00-05:00","timestamp":1721518200,"periods":{"first":1721518200,"second":1721521800},"venue":{"id":1619,"name":"Red Bull Arena","city":"Harrison, New Jersey"},"status":{"long":"Match Finished","short":"FT","elapsed":90}},"league":{"id":253,"name":"Major League Soccer","country":"USA","logo":"https://media.api-sports.io/football/leagues/253.png","flag":"https://media.api-sports.io/flags/us.svg","season":2024,"round":"Regular Season - 35"},"teams":{"home":{"id":1602,"name":"New York Red Bulls","logo":"https://media.api-sports.io/football/teams/1602.png","winner":true},"away":{"id":2242,"name":"FC Cincinnati","logo":"https://media.api-sports.io/football/teams/2242.png","winner":false}},"goals":{"home":3,"away":1},"score":{"halftime":{"home":1,"away":0},"fulltime":{"home":3,"away":1},"extratime":{"home":null,"away":null},"penalty":{"home":null,"away":null}}},{"fixture":{"id":1151110,"referee":"Joseph Dickerson, USA","timezone":"America/Bogota","date":"2024-07-20T18:30:00-05:00","timestamp":1721518200,"periods":{"first":1721518200,"second":1721521800},"venue":{"id":20500,"name":"Inter&Co Stadium","city":"Orlando, Florida"},"status":{"long":"Match Finished","short":"FT","elapsed":90}},"league":{"id":253,"name":"Major League Soccer","country":"USA","logo":"https://media.api-sports.io/football/leagues/253.png","flag":"https://media.api-sports.io/flags/us.svg","season":2024,"round":"Regular Season - 35"},"teams":{"home":{"id":1598,"name":"Orlando City SC","logo":"https://media.api-sports.io/football/teams/1598.png","winner":null},"away":{"id":1604,"name":"New York City FC","logo":"https://media.api-sports.io/football/teams/1604.png","winner":null}},"goals":{"home":1,"away":1},"score":{"halftime":{"home":0,"away":0},"fulltime":{"home":1,"away":1},"extratime":{"home":null,"away":null},"penalty":{"home":null,"away":null}}},{"fixture":{"id":1151111,"referee":"Chris Penso, USA","timezone":"America/Bogota","date":"2024-07-20T18:30:00-05:00","timestamp":1721518200,"periods":{"first":1721518200,"second":1721521800},"venue":{"id":1620,"name":"Subaru Park","city":"Chester, Pennsylvania"},"status":{"long":"Match Finished","short":"FT","elapsed":90}},"league":{"id":253,"name":"Major League Soccer","country":"USA","logo":"https://media.api-sports.io/football/leagues/253.png","flag":"https://media.api-sports.io/flags/us.svg","season":2024,"round":"Regular Season - 35"},"teams":{"home":{"id":1599,"name":"Philadelphia Union","logo":"https://media.api-sports.io/football/teams/1599.png","winner":true},"away":{"id":9569,"name":"Nashville SC","logo":"https://media.api-sports.io/football/teams/9569.png","winner":false}},"goals":{"home":3,"away":0},"score":{"halftime":{"home":2,"away":0},"fulltime":{"home":3,"away":0},"extratime":{"home":null,"away":null},"penalty":{"home":null,"away":null}}},{"fixture":{"id":1151112,"referee":"Jon Freemon, USA","timezone":"America/Bogota","date":"2024-07-20T19:30:00-05:00","timestamp":1721521800,"periods":{"first":1721521800,"second":1721525400},"venue":{"id":11535,"name":"Q2 Stadium","city":"Austin, Texas"},"status":{"long":"Match Finished","short":"FT","elapsed":90}},"league":{"id":253,"name":"Major League Soccer","country":"USA","logo":"https://media.api-sports.io/football/leagues/253.png","flag":"https://media.api-sports.io/flags/us.svg","season":2024,"round":"Regular Season - 35"},"teams":{"home":{"id":16489,"name":"Austin","logo":"https://media.api-sports.io/football/teams/16489.png","winner":null},"away":{"id":18310,"name":"Charlotte","logo":"https://media.api-sports.io/football/teams/18310.png","winner":null}},"goals":{"home":2,"away":2},"score":{"halftime":{"home":1,"away":1},"fulltime":{"home":2,"away":2},"extratime":{"home":null,"away":null},"penalty":{"home":null,"away":null}}},{"fixture":{"id":1151113,"referee":"Rubiel Vazquez, USA","timezone":"America/Bogota","date":"2024-07-20T19:30:00-05:00","timestamp":1721521800,"periods":{"first":1721521800,"second":1721525400},"venue":{"id":1615,"name":"Children's Mercy Park","city":"Kansas City, Kansas"},"status":{"long":"Match Finished","short":"FT","elapsed":90}},"league":{"id":253,"name":"Major League Soccer","country":"USA","logo":"https://media.api-sports.io/football/leagues/253.png","flag":"https://media.api-sports.io/flags/us.svg","season":2024,"round":"Regular Season - 35"},"teams":{"home":{"id":1611,"name":"Sporting Kansas City","logo":"https://media.api-sports.io/football/teams/1611.png","winner":null},"away":{"id":20787,"name":"St. Louis City","logo":"https://media.api-sports.io/football/teams/20787.png","winner":null}},"goals":{"home":1,"away":1},"score":{"halftime":{"home":0,"away":1},"fulltime":{"home":1,"away":1},"extratime":{"home":null,"away":null},"penalty":{"home":null,"away":null}}},{"fixture":{"id":1151114,"referee":"Ismir Pekmic, USA","timezone":"America/Bogota","date":"2024-07-20T19:30:00-05:00","timestamp":1721521800,"periods":{"first":1721521800,"second":1721525400},"venue":{"id":1617,"name":"Allianz Field","city":"Saint Paul, Minnesota"},"status":{"long":"Match Finished","short":"FT","elapsed":90}},"league":{"id":253,"name":"Major League Soccer","country":"USA","logo":"https://media.api-sports.io/football/leagues/253.png","flag":"https://media.api-sports.io/flags/us.svg","season":2024,"round":"Regular Season - 35"},"teams":{"home":{"id":1612,"name":"Minnesota United FC","logo":"https://media.api-sports.io/football/teams/1612.png","winner":true},"away":{"id":1596,"name":"San Jose Earthquakes","logo":"https://media.api-sports.io/football/teams/1596.png","winner":false}},"goals":{"home":2,"away":0},"score":{"halftime":{"home":1,"away":0},"fulltime":{"home":2,"away":0},"extratime":{"home":null,"away":null},"penalty":{"home":null,"away":null}}},{"fixture":{"id":1151115,"referee":"Ramy Touchan, USA","timezone":"America/Bogota","date":"2024-07-20T20:30:00-05:00","timestamp":1721525400,"periods":{"first":1721525400,"second":1721529000},"venue":{"id":1610,"name":"Dick's Sporting Goods Park","city":"Commerce City, Colorado"},"status":{"long":"Match Finished","short":"FT","elapsed":90}},"league":{"id":253,"name":"Major League Soccer","country":"USA","logo":"https://media.api-sports.io/football/leagues/253.png","flag":"https://media.api-sports.io/flags/us.svg","season":2024,"round":"Regular Season - 35"},"teams":{"home":{"id":1610,"name":"Colorado Rapids","logo":"https://media.api-sports.io/football/teams/1610.png","winner":true},"away":{"id":1606,"name":"Real Salt Lake","logo":"https://media.api-sports.io/football/teams/1606.png","winner":false}},"goals":{"home":3,"away":2},"score":{"halftime":{"home":2,"away":1},"fulltime":{"home":3,"away":2},"extratime":{"home":null,"away":null},"penalty":{"home":null,"away":null}}},{"fixture":{"id":1151116,"referee":"Sergiy Boyko, Ukraine","timezone":"America/Bogota","date":"2024-07-20T21:45:00-05:00","timestamp":1721529900,"periods":{"first":1721529900,"second":1721533500},"venue":{"id":1616,"name":"Dignity Health Sports Park","city":"Carson, California"},"status":{"long":"Match Finished","short":"FT","elapsed":90}},"league":{"id":253,"name":"Major League Soccer","country":"USA","logo":"https://media.api-sports.io/football/leagues/253.png","flag":"https://media.api-sports.io/flags/us.svg","season":2024,"round":"Regular Season - 35"},"teams":{"home":{"id":1605,"name":"Los Angeles Galaxy","logo":"https://media.api-sports.io/football/teams/1605.png","winner":true},"away":{"id":1617,"name":"Portland Timbers","logo":"https://media.api-sports.io/football/teams/1617.png","winner":false}},"goals":{"home":3,"away":2},"score":{"halftime":{"home":1,"away":0},"fulltime":{"home":3,"away":2},"extratime":{"home":null,"away":null},"penalty":{"home":null,"away":null}}},{"fixture":{"id":1151117,"referee":"Allen Chapman, USA","timezone":"America/Bogota","date":"2024-07-20T21:30:00-05:00","timestamp":1721529000,"periods":{"first":1721529000,"second":1721532600},"venue":{"id":11534,"name":"Lumen Field","city":"Seattle, Washington"},"status":{"long":"Match Finished","short":"FT","elapsed":90}},"league":{"id":253,"name":"Major League Soccer","country":"USA","logo":"https://media.api-sports.io/football/leagues/253.png","flag":"https://media.api-sports.io/flags/us.svg","season":2024,"round":"Regular Season - 35"},"teams":{"home":{"id":1595,"name":"Seattle Sounders","logo":"https://media.api-sports.io/football/teams/1595.png","winner":false},"away":{"id":1616,"name":"Los Angeles FC","logo":"https://media.api-sports.io/football/teams/1616.png","winner":true}},"goals":{"home":0,"away":3},"score":{"halftime":{"home":0,"away":2},"fulltime":{"home":0,"away":3},"extratime":{"home":null,"away":null},"penalty":{"home":null,"away":null}}}]}