{"get":"fixtures","parameters":{"league":"71","timezone":"America/Bogota","date":"2024-08-11","season":"2024"},"errors":[],"results":5,"paging":{"current":1,"total":1},"response":[{"fixture":{"id":1180574,"referee":"Flavio Rodrigues De Souza, Brazil","timezone":"America/Bogota","date":"2024-08-11T09:00:00-05:00","timestamp":1723384800,"periods":{"first":1723384800,"second":1723388400},"venue":{"id":248,"name":"Estádio Alfredo Jaconi","city":"Caxias do Sul, Rio Grande do Sul"},"status":{"long":"Match Finished","short":"FT","elapsed":90}},"league":{"id":71,"name":"Serie A","country":"Brazil","logo":"https://media.api-sports.io/football/leagues/71.png","flag":"https://media.api-sports.io/flags/br.svg","season":2024,"round":"Regular Season - 22"},"teams":{"home":{"id":152,"name":"Juventude","logo":"https://media.api-sports.io/football/teams/152.png","winner":true},"away":{"id":120,"name":"Botafogo","logo":"https://media.api-sports.io/football/teams/120.png","winner":false}},"goals":{"home":3,"away":2},"score":{"halftime":{"home":2,"away":0},"fulltime":{"home":3,"away":2},"extratime":{"home":null,"away":null},"penalty":{"home":null,"away":null}}},{"fixture":{"id":1180567,"referee":"Braulio Da Silva Machado, Brazil","timezone":"America/Bogota","date":"2024-08-11T14:00:00-05:00","timestamp":1723402800,"periods":{"first":1723402800,"second":1723406400},"venue":{"id":216,"name":"Arena Fonte Nova","city":"Salvador, Bahia"},"status":{"long":"Match Finished","short":"FT","elapsed":90}},"league":{"id":71,"name":"Serie A","country":"Brazil","logo":"https://media.api-sports.io/football/leagues/71.png","flag":"https://media.api-sports.io/flags/br.svg","season":2024,"round":"Regular Season - 22"},"teams":{"home":{"id":118,"name":"Bahia","logo":"https://media.api-sports.io/football/teams/118.png","winner":true},"away":{"id":136,"name":"Vitoria","logo":"https://media.api-sports.io/football/teams/136.png","winner":false}},"goals":{"home":2,"away":0},"score":{"halftime":{"home":1,"away":0},"fulltime":{"home":2,"away":0},"extratime":{"home":null,"away":null},"penalty":{"home":null,"away":null}}},{"fixture":{"id":1180568,"referee":"Wilton Pereira Sampaio, Brazil","timezone":"America/Bogota","date":"2024-08-11T14:00:00-05:00","timestamp":1723402800,"periods":{"first":1723402800,"second":1723406400},"venue":{"id":null,"name":"Estádio do Maracanã","city":"Rio de Janeiro"},"status":{"long":"Match Finished","short":"FT","elapsed":90}},"league":{"id":71,"name":"Serie A","country":"Brazil","logo":"https://media.api-sports.io/football/leagues/71.png","flag":"https://media.api-sports.io/flags/br.svg","season":2024,"round":"Regular Season - 22"},"teams":{"home":{"id":127,"name":"Flamengo","logo":"https://media.api-sports.io/football/teams/127.png","winner":null},"away":{"id":121,"name":"Palmeiras","logo":"https://media.api-sports.io/football/teams/121.png","winner":null}},"goals":{"home":1,"away":1},"score":{"halftime":{"home":0,"away":0},"fulltime":{"home":1,"away":1},"extratime":{"home":null,"away":null},"penalty":{"home":null,"away":null}}},{"fixture":{"id":1180571,"referee":"Davi de Oliveira Lacerda, Brazil","timezone":"America/Bogota","date":"2024-08-11T14:00:00-05:00","timestamp":1723402800,"periods":{"first":1723402800,"second":1723406400},"venue":{"id":20813,"name":"MorumBIS","city":"São Paulo, São Paulo"},"status":{"long":"Match Finished","short":"FT","elapsed":90}},"league":{"id":71,"name":"Serie A","country":"Brazil","logo":"https://media.api-sports.io/football/leagues/71.png","flag":"https://media.api-sports.io/flags/br.svg","season":2024,"round":"Regular Season - 22"},"teams":{"home":{"id":126,"name":"Sao Paulo","logo":"https://media.api-sports.io/football/teams/126.png","winner":true},"away":{"id":144,"name":"Atletico Goianiense","logo":"https://media.api-sports.io/football/teams/144.png","winner":false}},"goals":{"home":1,"away":0},"score":{"halftime":{"home":1,"away":0},"fulltime":{"home":1,"away":0},"extratime":{"home":null,"away":null},"penalty":{"home":null,"away":null}}},{"fixture":{"id":1180565,"referee":"Paulo Cesar Zanovelli da Silva, Brazil","timezone":"America/Bogota","date":"2024-08-11T17:00:00-05:00","timestamp":1723413600,"periods":{"first":1723413600,"second":1723417200},"venue":{"id":244,"name":"Estádio José Pinheiro Borda","city":"Porto Alegre, Rio Grande do Sul"},"status":{"long":"Match Finished","short":"FT","elapsed":90}},"league":{"id":71,"name":"Serie A","country":"Brazil","logo":"https://media.api-sports.io/football/leagues/71.png","flag":"https://media.api-sports.io/flags/br.svg","season":2024,"round":"Regular Season - 22"},"teams":{"home":{"id":119,"name":"Internacional","logo":"https://media.api-sports.io/football/teams/119.png","winner":null},"away":{"id":134,"name":"Atletico Paranaense","logo":"https://media.api-sports.io/football/teams/134.png","winner":null}},"goals":{"home":2,"away":2},"score":{"halftime":{"home":1,"away":1},"fulltime":{"home":2,"away":2},"extratime":{"home":null,"away":null},"penalty":{"home":null,"away":null}}}]}